.gitignore
LICENSE
MANIFEST.in
NOTICE
README.rst
THANKS
requirements_dev.txt
requirements_test.txt
setup.cfg
setup.py
docs/Makefile
docs/README.rst
docs/gunicorn_ext.py
docs/make.bat
docs/sitemap_gen.py
docs/logo/gunicorn.png
docs/logo/gunicorn.svg
docs/site/.nojekyll
docs/site/CNAME
docs/site/community.html
docs/site/configuration.html
docs/site/configure.html
docs/site/deploy.html
docs/site/deployment.html
docs/site/design.html
docs/site/faq.html
docs/site/index.html
docs/site/install.html
docs/site/installation.html
docs/site/news.html
docs/site/run.html
docs/site/sitemap.xml
docs/site/tuning.html
docs/site/usage.html
docs/site/css/style.css
docs/site/images/about.jpg
docs/site/images/arrow.png
docs/site/images/banner-bg.jpg
docs/site/images/community.jpg
docs/site/images/documents.jpg
docs/site/images/downloads.jpg
docs/site/images/favicon.png
docs/site/images/footer-arrow.png
docs/site/images/footer-logo.jpg
docs/site/images/greenbutton.jpg
docs/site/images/gunicorn.png
docs/site/images/large_gunicorn.png
docs/site/images/logo-bottom.png
docs/site/images/logo.jpg
docs/site/images/logo.png
docs/site/images/redbutton.jpg
docs/site/images/separator.jpg
docs/site/images/title.png
docs/site/images/user1.jpg
docs/site/js/main.js
docs/source/2010-news.rst
docs/source/2011-news.rst
docs/source/2012-news.rst
docs/source/2013-news.rst
docs/source/2014-news.rst
docs/source/2015-news.rst
docs/source/2016-news.rst
docs/source/2017-news.rst
docs/source/2018-news.rst
docs/source/2019-news.rst
docs/source/2020-news.rst
docs/source/2021-news.rst
docs/source/community.rst
docs/source/conf.py
docs/source/configure.rst
docs/source/custom.rst
docs/source/deploy.rst
docs/source/design.rst
docs/source/faq.rst
docs/source/index.rst
docs/source/install.rst
docs/source/instrumentation.rst
docs/source/news.rst
docs/source/run.rst
docs/source/settings.rst
docs/source/signals.rst
docs/source/_static/gunicorn.png
examples/alt_spec.py
examples/bad.py
examples/boot_fail.py
examples/echo.py
foodalgo_gunicorn.egg-info/PKG-INFO
foodalgo_gunicorn.egg-info/SOURCES.txt
foodalgo_gunicorn.egg-info/dependency_links.txt
foodalgo_gunicorn.egg-info/entry_points.txt
foodalgo_gunicorn.egg-info/not-zip-safe
foodalgo_gunicorn.egg-info/requires.txt
foodalgo_gunicorn.egg-info/top_level.txt
