Metadata-Version: 2.1
Name: foodalgo-gunicorn
Version: 1.0.1
Summary: WSGI HTTP Server for UNIX
Home-page: https://gunicorn.org
Author: yungkit
Author-email: ginolai@qq.com
License: MIT
Project-URL: Documentation, https://docs.gunicorn.org
Project-URL: Homepage, https://gunicorn.org
Project-URL: Issue tracker, https://github.com/benoitc/gunicorn/issues
Project-URL: Source code, https://github.com/benoitc/gunicorn
Platform: UNKNOWN
Classifier: Development Status :: 5 - Production/Stable
Classifier: Environment :: Other Environment
Classifier: Intended Audience :: Developers
Classifier: License :: OSI Approved :: MIT License
Classifier: Operating System :: MacOS :: MacOS X
Classifier: Operating System :: POSIX
Classifier: Programming Language :: Python
Classifier: Programming Language :: Python :: 3
Classifier: Programming Language :: Python :: 3.5
Classifier: Programming Language :: Python :: 3.6
Classifier: Programming Language :: Python :: 3.7
Classifier: Programming Language :: Python :: 3.8
Classifier: Programming Language :: Python :: 3.9
Classifier: Programming Language :: Python :: 3 :: Only
Classifier: Programming Language :: Python :: Implementation :: CPython
Classifier: Programming Language :: Python :: Implementation :: PyPy
Classifier: Topic :: Internet
Classifier: Topic :: Utilities
Classifier: Topic :: Software Development :: Libraries :: Python Modules
Classifier: Topic :: Internet :: WWW/HTTP
Classifier: Topic :: Internet :: WWW/HTTP :: WSGI
Classifier: Topic :: Internet :: WWW/HTTP :: WSGI :: Server
Classifier: Topic :: Internet :: WWW/HTTP :: Dynamic Content
Requires-Python: >=3.5
Provides-Extra: gevent
Provides-Extra: eventlet
Provides-Extra: tornado
Provides-Extra: gthread
Provides-Extra: setproctitle
